{"title":"JR Android Developer NEW!","location":"","salary":"","description":"","term":"Full-Time","detail":"https://www.ziprecruiter.com/k/l/AALaUwrSEgA0sCkmKXbc6L-Wz_JLLCKXpzhBKkicqOdcdTozadpz_Z4SHAUjhcgDX8bS_G745dtD51y4YYuxdzpFV8H1bYmB_Ovou695QVIip2jK1qFw_d0oyH5K8Q4Ez3-b8ZI70DKJ2fzoCPZLkaFOJXvFq4dFG6nz9GrMRfJfi2wD0mx1lBQBQnc3vLc","source":"ziprecruiter","full_description":"You will be a co-located member of the engineering team, working with both internal and sourced mobile app developers driving a consistent high quality product across Android and iOS for customers. Our current mobile solution handles secure actions, notifications, asynchronous transactions, and leverages various device hardware and security from biometric capabilities, Bluetooth communication, accelerometer & gyroscope data, as well as secure enclave storage. Self-motivation and a personal strive for building great things is a must for this role. Android Associate Developer Responsibilities:Designing and building mobile applications for Google’s Android platformCollaborating with the team to define app featuresEnsuring quality and performance of applicationsIdentifying potential problems and resolving performance bottlenecksFixing application bugsDesigning and implementing application featuresAndroid Associate Developer Requirements:Bachelor’s degree in Computer Science or Software EngineeringProficient in Java and KotlinThorough understanding of memory management and the Android application lifecycleExperience with retrieving data from a backend service using OkHttpUnderstanding of concurrent programming and the tools available on AndroidKnowledge of Material design principles and componentsCompetent in the use of Android Studio for both writing code and debuggingExperience with Git for version controlAdditionally, it could be valuable if you had any of the following:Experience developing for iOS devicesTo be successful in this role, you must be a highly motivated individual who is experienced enough to plan ahead and document your work amidst a fast-paced environment."}