{"title":"Senior Developer","location":"San Diego, CA 92127 (Rancho Bernardo area)","salary":"\n\n$88,505 - $125,000 a year\n","description":"\n<ul style=\"list-style-type:circle;margin-top: 0px;margin-bottom: 0px;padding-left:20px;\"> \n <li style=\"margin-bottom:0px;\">NET 4.5/4.0, 3.5, MVC 4.0, Entity Framework, JQuery, Xamarin (MonoTouch) for app development.</li>\n <li>AJAX, Microsoft SQL Server 2012, Visual Studio 2012 and Active…</li>\n</ul>","term":1,"jk":"f20e7c1d0b6573c8","detail":"https://www.indeed.com/viewjob?viewtype=embedded&jk=f20e7c1d0b6573c8","source":"indeed"}