{"title":"Sterling OMS Developer","location":"","salary":"","description":"","term":"Contractor","detail":"https://www.ziprecruiter.com/k/l/AAJ3A434TTxf6JYgrZ1sX9qKCqBuRqydu0bHQwMEeTWPVkfC6c6JBXEgbe9LAQ61j80CVL5OYiIWOmJH1ozTcWG9Asi0oxC8x5V6KLo99XUmjea0hDrEEK0Apr4HVpzWuc-4q00NjblOdyVqb1UqGGLVyQqJi9Jn18sOxW9-ECAo8A4I_kto5L_03aiJdpc","source":"ziprecruiter","full_description":"We are seeking a Sterling OMS Developer to become an integral part of our team! You will be responsible for creating and modifying computer application software or specialized utility programs.Responsibilities:Analyze user needs and develop software solutionsWork with the project manager or product owner to meet specification needsDesign develop and test applications in accordance with established requirements, standards, processes, and best practicesRecommend software upgrades to optimize operational efficiencyLead and participate in medium- to large-scale projects and propose high-level designResponsible for designing and developing new features and troubleshoots with the application groups which interface with the Sterling OMS applicationCollaborate with other developers to design and optimize codeParticipate in overall development and deployment process, in a Business-Driven and continuous integration environment.Create flowcharts and user guides for new and existing programsDocument all programming tasks and proceduresCollaborate within an Agile dynamic development environment & eager to learn technologies.Perform routine software maintenanceQualifications:Bachelor’s degree in Computer Science, Engineering or related field5 years of experience in Software Development or related occupationKnowledge of Java, Python, or other programming languagesFamiliarity with relational databases such as MySQL, Oracle, and SQL ServerDeadline and detail-orientedWorking knowledge on Shell Scripts, and XML, Sterling Commerce’s complementary and competitive products such as Kafka, WebSphere, MQ Series, or JMS compliant queues5+ Years of Strong experience in Java, J2EE, and software design patternsStrong analytical and critical thinking skills"}